pos_tagging/__init__.py
pos_tagging/main.py
pos_tagging-0.6.5.dist-info/METADATA
pos_tagging-0.6.5.dist-info/WHEEL
pos_tagging-0.6.5.dist-info/entry_points.txt
pos_tagging-0.6.5.dist-info/top_level.txt
pos_tagging-0.6.5.dist-info/RECORD
