Metadata-Version: 2.1
Name: pos_tagging
Version: 0.6.5
Requires-Dist: langchain-google-genai>=2.0.0
